LICENSE
MANIFEST.in
README.rst
setup.py
django_dms/__init__.py
django_dms/admin.py
django_dms/apps.py
django_dms/models.py
django_dms/tests.py
django_dms/views.py
django_dms.egg-info/PKG-INFO
django_dms.egg-info/SOURCES.txt
django_dms.egg-info/dependency_links.txt
django_dms.egg-info/top_level.txt
django_dms/migrations/__init__.py
django_dms/templatetags/dms.py
django_dms/templatetags/__pycache__/dms.cpython-35.pyc