Metadata-Version: 1.2
Name: django-dms
Version: 0.1.1b0
Summary: A Django template filter for displaying longitude and  latitude in degrees-minutes-seconds notation
Home-page: https://github.com/cezar77/django-dms
Author: Cezar Pendarovski
Author-email: cezarpendarovski@web.de
Maintainer: Cezar Pendarovski
Maintainer-email: cezarpendarovski@web.de
License: GPL-3.0
Platform: UNKNOWN
Classifier: Development Status :: 4 - Beta
Classifier: Environment :: Web Environment
Classifier: Intended Audience :: Developers
Classifier: License :: OSI Approved :: GNU General Public License v3 or later (GPLv3+)
Classifier: Operating System :: OS Independent
Classifier: Programming Language :: Python
Classifier: Programming Language :: Python :: 3
Classifier: Framework :: Django
